{
  "testButton": "Toggle Preview",
  "layout": "1",
  "rankCount": 4,
  "levelPrefix": "Level",
  "removeCommand": "!deleterank",
  "displayEmote": "flex",
  "defaultEmote": "https://cdn.streamelements.com/uploads/42e2c327-5bc1-4b20-b954-3063b55908d5.png",
  "minXP": 1,
  "maxXP": 1,
  "messagesPerMin": 100,
  "charMin": 0,
  "initialLevelXP": 10,
  "xpIncrease": 10,
  "ignoreCommands": "true",
  "ignoreList": "StreamElements, TwitchBot, TwitchUser",
  "mainBackgroundColor": "transparent",
  "mainBorderColor": "black",
  "mainBorderWidth": 0,
  "mainBorderRadius": 0,
  "mainPadding": "30px 30px 30px 30px",
  "mainOuterShadowColor": "black",
  "mainInnerShadowColor": "black",
  "mainInnerShadowOffset": "0px 0px",
  "mainInnerShadowBlur": 0,
  "mainInnerShadowSpread": 0,
  "rankBackgroundColor": "#a9e694",
  "rankBorderColor": "#6ec451",
  "rankBorderWidth": 2,
  "rankBorderRadius": 20,
  "rankPadding": "10px 10px 10px 10px",
  "rankMargin": "0px 0px 20px 0px",
  "rankOuterShadowColor": "#6ec451",
  "rankOuterShadowOffset": "2px 2px",
  "rankOuterShadowBlur": 0,
  "rankOuterShadowSpread": 1,
  "rankInnerShadowColor": "#cefcbe",
  "rankInnerShadowOffset": "2px 10px",
  "rankInnerShadowBlur": 30,
  "rankInnerShadowSpread": 1,
  "levelBoxBackgroundColor": "transparent",
  "levelBoxBorderColor": "black",
  "levelBoxBorderWidth": 0,
  "levelBoxBorderRadius": 0,
  "levelBoxPadding": "0px 0px 0px 0px",
  "levelBoxMargin": "0px 5px 0px 0px",
  "levelBoxOuterShadowColor": "black",
  "levelBoxOuterShadowOffset": "0px 0px",
  "levelBoxOuterShadowBlur": 0,
  "levelBoxOuterShadowSpread": 0,
  "levelBoxInnerShadowColor": "black",
  "levelBoxInnerShadowOffset": "0px 0px",
  "levelBoxInnerShadowBlur": 0,
  "levelBoxInnerShadowSpread": 0,
  "levelColor": "#2d7c13",
  "levelFont": "Nunito",
  "levelSize": 16,
  "levelWeight": "normal",
  "levelShadowColor": "#6ec451",
  "levelShadowOffset": "0px 0px",
  "levelShadowBlur": 0,
  "usernameBoxBackgroundColor": "transparent",
  "usernameBoxBorderColor": "black",
  "usernameBoxBorderWidth": 0,
  "usernameBoxBorderRadius": 0,
  "usernameBoxPadding": "0px 0px 2px 0px",
  "usernameBoxMargin": "0px 0px 0px 2px",
  "usernameBoxOuterShadowColor": "black",
  "usernameBoxOuterShadowOffset": "0px 0px",
  "usernameBoxOuterShadowBlur": 0,
  "usernameBoxOuterShadowSpread": 0,
  "usernameBoxInnerShadowColor": "black",
  "usernameBoxInnerShadowOffset": "0px 0px",
  "usernameBoxInnerShadowBlur": 0,
  "usernameBoxInnerShadowSpread": 0,
  "usernameColor": "#2d7c13",
  "usernameFont": "Nunito",
  "usernameSize": 20,
  "usernameWeight": "normal",
  "usernameShadowColor": "#6ec451",
  "usernameShadowOffset": "0px 0px",
  "usernameShadowBlur": 0,
  "xpBoxBackgroundColor": "#6ec451",
  "xpBoxBorderColor": "black",
  "xpBoxBorderWidth": 0,
  "xpBoxBorderRadius": 10,
  "xpBoxMinHeight": 25,
  "xpBoxPadding": "5px 5px 5px 5px",
  "xpBoxMargin": "0px 0px 0px 0px",
  "xpBoxOuterShadowColor": "black",
  "xpBoxOuterShadowOffset": "0px 0px",
  "xpBoxOuterShadowBlur": 0,
  "xpBoxOuterShadowSpread": 0,
  "xpBoxInnerShadowColor": "#429627",
  "xpBoxInnerShadowOffset": "2px 2px",
  "xpBoxInnerShadowBlur": 8,
  "xpBoxInnerShadowSpread": 0,
  "xpBackgroundColor": "#a9e694",
  "xpBorderColor": "transparent",
  "xpBorderWidth": 0,
  "xpBorderRadius": 5,
  "xpPadding": "0px 0px 0px 0px",
  "xpMargin": "0px 0px 0px 0px",
  "xpOuterShadowColor": "black",
  "xpOuterShadowOffset": "0px 0px",
  "xpOuterShadowBlur": 0,
  "xpOuterShadowSpread": 0,
  "xpInnerShadowColor": "#cefcbe",
  "xpInnerShadowOffset": "2px 5px",
  "xpInnerShadowBlur": 10,
  "xpInnerShadowSpread": 1,
  "emoteBoxBackgroundColor": "transparent",
  "emoteBoxBorderColor": "black",
  "emoteBoxBorderWidth": 0,
  "emoteBoxBorderRadius": 50,
  "emoteBoxPadding": "0px 0px 0px 0px",
  "emoteBoxMargin": "0px 10px 0px 0px",
  "emoteBoxOuterShadowColor": "black",
  "emoteBoxOuterShadowOffset": "0px 0px",
  "emoteBoxOuterShadowBlur": 0,
  "emoteBoxOuterShadowSpread": 0,
  "emoteBoxInnerShadowColor": "black",
  "emoteBoxInnerShadowOffset": "0px 0px",
  "emoteBoxInnerShadowBlur": 0,
  "emoteBoxInnerShadowSpread": 0,
  "emoteSize": 50,
  "emoteShadowColor": "#429627",
  "emoteShadowOffset": "0px 1px",
  "emoteShadowBlur": 0,
  "widgetName": "Chat Leaderboard",
  "widgetAuthor": "Zaytri",
  "widgetVersion": "2.2.4",
  "widgetUpdateUrl": "https://github.com/zaytri/stream-elements-widgets/blob/main/LevelUp",
  "enableAdvanced": "false",
  "apiToken": "Copy/paste API token here",
  "rankCommand": "!rank",
  "rankCommandCooldown": 60
}